{
  "Game": "game",
  "UpdateGame": "UpdateGame",
  "DeleteGame": "deleteGame",
  "AddGame": "addGame",
  "Games": "games",

  "Genres": "genres",
  "Genre": "genre",
  "AddGenre": "addGenre",
  "DeleteGenre": "deleteGenre",
  "UpdateGenre": "updateGenre",

  "UpdatePlatform": "updatePlatform",
  "DeletePlatform": "deletePlatform",
  "Platform": "platform",
  "AddPlatform": "addPlatform",
  "Platforms": "platforms",

  "Publishers": "publishers",
  "Publisher": "publisher",
  "UpdatePublisher": "updatePublisher",
  "DeletePublisher": "deletePublisher",
  "AddPublisher": "addPublisher",

  "Order": "order",
  "UpdateOrder": "updateOrder",
  "History": "history",
  "Orders": "orders",
  "Basket": "basket",
  "MakeOrder": "makeOrder",

  "Users": "users",
  "User": "user",
  "UpdateUser": "updateUser",
  "DeleteUser": "deleteUser",
  "AddUser": "addUser",
  "Login": "login",

  "Roles": "roles",
  "Role": "role",
  "UpdateRole": "updateRole",
  "DeleteRole": "deleteRole",
  "AddRole": "addRole"
}
